{
  "nodes": [
    {
      "id": 0,
      "word": "His",
      "lemma": "his",
      "pos": "PRON",
      "dep": "poss",
      "node_type": 0,
      "node_type_str": "NOUN",
      "okm_notation": "His(1,1,6)",
      "ambiguous": false,
      "gender": 1,
      "number": 1,
      "case": 6,
      "case_str": "GENITIVE",
      "person": -1,
      "tense": 0
    },
    {
      "id": 1,
      "word": "main",
      "lemma": "main",
      "pos": "ADJ",
      "dep": "amod",
      "node_type": 2,
      "node_type_str": "DESCRIPTOR",
      "okm_notation": "[d:main]",
      "ambiguous": false,
      "gender": -1,
      "number": -1,
      "case": -1,
      "person": -1,
      "tense": 0
    },
    {
      "id": 2,
      "word": "breaking",
      "lemma": "breaking",
      "pos": "NOUN",
      "dep": "amod",
      "node_type": 0,
      "node_type_str": "NOUN",
      "okm_notation": "breaking(3,1,2)",
      "ambiguous": false,
      "gender": 3,
      "number": 1,
      "case": 2,
      "case_str": "OBJECTIVE",
      "person": -1,
      "tense": 0
    },
    {
      "id": 3,
      "word": "ball",
      "lemma": "ball",
      "pos": "NOUN",
      "dep": "nsubj",
      "node_type": 0,
      "node_type_str": "NOUN",
      "okm_notation": "ball(3,1,1)",
      "ambiguous": false,
      "gender": 3,
      "number": 1,
      "case": 1,
      "case_str": "SUBJECTIVE",
      "person": -1,
      "tense": 0
    },
    {
      "id": 4,
      "word": "is",
      "lemma": "be",
      "pos": "AUX",
      "dep": "ROOT",
      "node_type": 1,
      "node_type_str": "VERB",
      "okm_notation": "is(3,1,999)",
      "ambiguous": false,
      "person": 3,
      "v_number": 1,
      "tense": 0,
      "tense_str": "PRESENT",
      "gender": -1,
      "number": -1,
      "case": -1
    },
    {
      "id": 5,
      "word": "a",
      "lemma": "a",
      "pos": "DET",
      "dep": "det",
      "node_type": 2,
      "node_type_str": "DESCRIPTOR",
      "okm_notation": "[d:a]",
      "ambiguous": false,
      "gender": -1,
      "number": -1,
      "case": -1,
      "person": -1,
      "tense": 0
    },
    {
      "id": 6,
      "word": "hard",
      "lemma": "hard",
      "pos": "ADJ",
      "dep": "amod",
      "node_type": 2,
      "node_type_str": "DESCRIPTOR",
      "okm_notation": "[d:hard]",
      "ambiguous": false,
      "gender": -1,
      "number": -1,
      "case": -1,
      "person": -1,
      "tense": 0
    },
    {
      "id": 7,
      "word": "slider",
      "lemma": "slider",
      "pos": "NOUN",
      "dep": "attr",
      "node_type": 0,
      "node_type_str": "NOUN",
      "okm_notation": "slider(3,1,2)",
      "ambiguous": false,
      "gender": 3,
      "number": 1,
      "case": 2,
      "case_str": "OBJECTIVE",
      "person": -1,
      "tense": 0
    },
    {
      "id": 8,
      "word": "in",
      "lemma": "in",
      "pos": "ADP",
      "dep": "prep",
      "node_type": 2,
      "node_type_str": "DESCRIPTOR",
      "okm_notation": "[d:in]",
      "ambiguous": false,
      "gender": -1,
      "number": -1,
      "case": -1,
      "person": -1,
      "tense": 0
    },
    {
      "id": 9,
      "word": "the",
      "lemma": "the",
      "pos": "DET",
      "dep": "det",
      "node_type": 2,
      "node_type_str": "DESCRIPTOR",
      "okm_notation": "[d:the]",
      "ambiguous": false,
      "gender": -1,
      "number": -1,
      "case": -1,
      "person": -1,
      "tense": 0
    },
    {
      "id": 10,
      "word": "upper",
      "lemma": "upper",
      "pos": "ADJ",
      "dep": "amod",
      "node_type": 2,
      "node_type_str": "DESCRIPTOR",
      "okm_notation": "[d:upper]",
      "ambiguous": false,
      "gender": -1,
      "number": -1,
      "case": -1,
      "person": -1,
      "tense": 0
    },
    {
      "id": 11,
      "word": "80s",
      "lemma": "80",
      "pos": "NOUN",
      "dep": "pobj",
      "node_type": 0,
      "node_type_str": "NOUN",
      "okm_notation": "80s(3,3,7)",
      "ambiguous": false,
      "gender": 3,
      "number": 3,
      "case": 7,
      "case_str": "LOCATIVE",
      "person": -1,
      "tense": 0
    },
    {
      "id": 13,
      "word": "occasionally",
      "lemma": "occasionally",
      "pos": "ADV",
      "dep": "advmod",
      "node_type": 2,
      "node_type_str": "DESCRIPTOR",
      "okm_notation": "[d:occasionally]",
      "ambiguous": false,
      "gender": -1,
      "number": -1,
      "case": -1,
      "person": -1,
      "tense": 0
    },
    {
      "id": 14,
      "word": "even",
      "lemma": "even",
      "pos": "ADV",
      "dep": "advmod",
      "node_type": 2,
      "node_type_str": "DESCRIPTOR",
      "okm_notation": "[d:even]",
      "ambiguous": false,
      "gender": -1,
      "number": -1,
      "case": -1,
      "person": -1,
      "tense": 0
    },
    {
      "id": 15,
      "word": "touching",
      "lemma": "touch",
      "pos": "VERB",
      "dep": "advcl",
      "node_type": 1,
      "node_type_str": "VERB",
      "okm_notation": "touching(3,1,999)",
      "ambiguous": false,
      "person": 3,
      "v_number": 1,
      "tense": 0,
      "tense_str": "PRESENT",
      "gender": -1,
      "number": -1,
      "case": -1
    },
    {
      "id": 16,
      "word": "90",
      "lemma": "90",
      "pos": "NUM",
      "dep": "dobj",
      "node_type": 2,
      "node_type_str": "DESCRIPTOR",
      "okm_notation": "[d:90]",
      "ambiguous": false,
      "gender": -1,
      "number": -1,
      "case": -1,
      "person": -1,
      "tense": 0
    }
  ],
  "edges": [
    {
      "source": 3,
      "target": 0,
      "dep": "poss",
      "relation": "POSSESSES",
      "case": 6,
      "case_str": "GENITIVE",
      "child_type": "NOUN",
      "head_type": "NOUN"
    },
    {
      "source": 3,
      "target": 1,
      "dep": "amod",
      "relation": "AMOD",
      "case": -1,
      "case_str": "NONE",
      "child_type": "DESCRIPTOR",
      "head_type": "NOUN"
    },
    {
      "source": 3,
      "target": 2,
      "dep": "amod",
      "relation": "OBJECT_OF",
      "case": 2,
      "case_str": "OBJECTIVE",
      "child_type": "NOUN",
      "head_type": "NOUN"
    },
    {
      "source": 4,
      "target": 3,
      "dep": "nsubj",
      "relation": "SUBJECT_OF",
      "case": 1,
      "case_str": "SUBJECTIVE",
      "child_type": "NOUN",
      "head_type": "VERB"
    },
    {
      "source": 4,
      "target": 7,
      "dep": "attr",
      "relation": "OBJECT_OF",
      "case": 2,
      "case_str": "OBJECTIVE",
      "child_type": "NOUN",
      "head_type": "VERB"
    },
    {
      "source": 4,
      "target": 15,
      "dep": "advcl",
      "relation": "ADVCL",
      "case": -1,
      "case_str": "NONE",
      "child_type": "VERB",
      "head_type": "VERB"
    },
    {
      "source": 7,
      "target": 5,
      "dep": "det",
      "relation": "DET",
      "case": -1,
      "case_str": "NONE",
      "child_type": "DESCRIPTOR",
      "head_type": "NOUN"
    },
    {
      "source": 7,
      "target": 6,
      "dep": "amod",
      "relation": "AMOD",
      "case": -1,
      "case_str": "NONE",
      "child_type": "DESCRIPTOR",
      "head_type": "NOUN"
    },
    {
      "source": 7,
      "target": 8,
      "dep": "prep",
      "relation": "PREP",
      "case": -1,
      "case_str": "NONE",
      "child_type": "DESCRIPTOR",
      "head_type": "NOUN"
    },
    {
      "source": 8,
      "target": 11,
      "dep": "pobj",
      "relation": "LOCATED_AT",
      "case": 7,
      "case_str": "LOCATIVE",
      "child_type": "NOUN",
      "head_type": "DESCRIPTOR"
    },
    {
      "source": 11,
      "target": 9,
      "dep": "det",
      "relation": "DET",
      "case": -1,
      "case_str": "NONE",
      "child_type": "DESCRIPTOR",
      "head_type": "NOUN"
    },
    {
      "source": 11,
      "target": 10,
      "dep": "amod",
      "relation": "AMOD",
      "case": -1,
      "case_str": "NONE",
      "child_type": "DESCRIPTOR",
      "head_type": "NOUN"
    },
    {
      "source": 15,
      "target": 13,
      "dep": "advmod",
      "relation": "ADVMOD",
      "case": -1,
      "case_str": "NONE",
      "child_type": "DESCRIPTOR",
      "head_type": "VERB"
    },
    {
      "source": 15,
      "target": 14,
      "dep": "advmod",
      "relation": "ADVMOD",
      "case": -1,
      "case_str": "NONE",
      "child_type": "DESCRIPTOR",
      "head_type": "VERB"
    },
    {
      "source": 15,
      "target": 16,
      "dep": "dobj",
      "relation": "DOBJ",
      "case": -1,
      "case_str": "NONE",
      "child_type": "DESCRIPTOR",
      "head_type": "VERB"
    }
  ],
  "meta": {
    "okm_version": "1.0",
    "sentence": "His main breaking ball is a hard slider in the upper 80s , occasionally even touching 90 ."
  }
}