{
  "nodes": [
    {
      "id": 0,
      "word": "When",
      "lemma": "when",
      "pos": "SCONJ",
      "dep": "advmod",
      "node_type": 2,
      "node_type_str": "DESCRIPTOR",
      "okm_notation": "[d:When]",
      "ambiguous": false,
      "gender": -1,
      "number": -1,
      "case": -1,
      "person": -1,
      "tense": 0
    },
    {
      "id": 1,
      "word": "the",
      "lemma": "the",
      "pos": "DET",
      "dep": "det",
      "node_type": 2,
      "node_type_str": "DESCRIPTOR",
      "okm_notation": "[d:the]",
      "ambiguous": false,
      "gender": -1,
      "number": -1,
      "case": -1,
      "person": -1,
      "tense": 0
    },
    {
      "id": 2,
      "word": "new",
      "lemma": "new",
      "pos": "ADJ",
      "dep": "amod",
      "node_type": 2,
      "node_type_str": "DESCRIPTOR",
      "okm_notation": "[d:new]",
      "ambiguous": false,
      "gender": -1,
      "number": -1,
      "case": -1,
      "person": -1,
      "tense": 0
    },
    {
      "id": 3,
      "word": "hospital",
      "lemma": "hospital",
      "pos": "NOUN",
      "dep": "nsubj",
      "node_type": 0,
      "node_type_str": "NOUN",
      "okm_notation": "hospital(3,1,1)",
      "ambiguous": false,
      "gender": 3,
      "number": 1,
      "case": 1,
      "case_str": "SUBJECTIVE",
      "person": -1,
      "tense": 0
    },
    {
      "id": 4,
      "word": "is",
      "lemma": "be",
      "pos": "AUX",
      "dep": "advcl",
      "node_type": 1,
      "node_type_str": "VERB",
      "okm_notation": "is(3,1,999)",
      "ambiguous": false,
      "person": 3,
      "v_number": 1,
      "tense": 0,
      "tense_str": "PRESENT",
      "gender": -1,
      "number": -1,
      "case": -1
    },
    {
      "id": 5,
      "word": "complete",
      "lemma": "complete",
      "pos": "ADJ",
      "dep": "acomp",
      "node_type": 2,
      "node_type_str": "DESCRIPTOR",
      "okm_notation": "[d:complete]",
      "ambiguous": false,
      "gender": -1,
      "number": -1,
      "case": -1,
      "person": -1,
      "tense": 0
    },
    {
      "id": 7,
      "word": "along",
      "lemma": "along",
      "pos": "ADP",
      "dep": "prep",
      "node_type": 2,
      "node_type_str": "DESCRIPTOR",
      "okm_notation": "[d:along]",
      "ambiguous": false,
      "gender": -1,
      "number": -1,
      "case": -1,
      "person": -1,
      "tense": 0
    },
    {
      "id": 8,
      "word": "with",
      "lemma": "with",
      "pos": "ADP",
      "dep": "prep",
      "node_type": 2,
      "node_type_str": "DESCRIPTOR",
      "okm_notation": "[d:with]",
      "ambiguous": false,
      "gender": -1,
      "number": -1,
      "case": -1,
      "person": -1,
      "tense": 0
    },
    {
      "id": 9,
      "word": "the",
      "lemma": "the",
      "pos": "DET",
      "dep": "det",
      "node_type": 2,
      "node_type_str": "DESCRIPTOR",
      "okm_notation": "[d:the]",
      "ambiguous": false,
      "gender": -1,
      "number": -1,
      "case": -1,
      "person": -1,
      "tense": 0
    },
    {
      "id": 10,
      "word": "renovations",
      "lemma": "renovation",
      "pos": "NOUN",
      "dep": "pobj",
      "node_type": 0,
      "node_type_str": "NOUN",
      "okm_notation": "renovations(3,3,3)",
      "ambiguous": false,
      "gender": 3,
      "number": 3,
      "case": 3,
      "case_str": "INSTRUMENTAL",
      "person": -1,
      "tense": 0
    },
    {
      "id": 11,
      "word": "at",
      "lemma": "at",
      "pos": "ADP",
      "dep": "prep",
      "node_type": 2,
      "node_type_str": "DESCRIPTOR",
      "okm_notation": "[d:at]",
      "ambiguous": false,
      "gender": -1,
      "number": -1,
      "case": -1,
      "person": -1,
      "tense": 0
    },
    {
      "id": 12,
      "word": "John",
      "lemma": "John",
      "pos": "PROPN",
      "dep": "compound",
      "node_type": 0,
      "node_type_str": "NOUN",
      "okm_notation": "John(3,1,6)",
      "ambiguous": false,
      "gender": 3,
      "number": 1,
      "case": 6,
      "case_str": "GENITIVE",
      "person": -1,
      "tense": 0
    },
    {
      "id": 13,
      "word": "Sealy",
      "lemma": "Sealy",
      "pos": "PROPN",
      "dep": "pobj",
      "node_type": 0,
      "node_type_str": "NOUN",
      "okm_notation": "Sealy(3,1,7)",
      "ambiguous": false,
      "gender": 3,
      "number": 1,
      "case": 7,
      "case_str": "LOCATIVE",
      "person": -1,
      "tense": 0
    },
    {
      "id": 15,
      "word": "both",
      "lemma": "both",
      "pos": "DET",
      "dep": "det",
      "node_type": 2,
      "node_type_str": "DESCRIPTOR",
      "okm_notation": "[d:both]",
      "ambiguous": false,
      "gender": -1,
      "number": -1,
      "case": -1,
      "person": -1,
      "tense": 0
    },
    {
      "id": 16,
      "word": "complexes",
      "lemma": "complex",
      "pos": "NOUN",
      "dep": "nsubj",
      "node_type": 0,
      "node_type_str": "NOUN",
      "okm_notation": "complexes(3,3,1)",
      "ambiguous": false,
      "gender": 3,
      "number": 3,
      "case": 1,
      "case_str": "SUBJECTIVE",
      "person": -1,
      "tense": 0
    },
    {
      "id": 17,
      "word": "will",
      "lemma": "will",
      "pos": "AUX",
      "dep": "aux",
      "node_type": 1,
      "node_type_str": "VERB",
      "okm_notation": "will(3,1,999)",
      "ambiguous": false,
      "person": 3,
      "v_number": 1,
      "tense": 0,
      "tense_str": "PRESENT",
      "gender": -1,
      "number": -1,
      "case": -1
    },
    {
      "id": 18,
      "word": "have",
      "lemma": "have",
      "pos": "VERB",
      "dep": "ROOT",
      "node_type": 1,
      "node_type_str": "VERB",
      "okm_notation": "have(3,3,1)",
      "ambiguous": false,
      "person": 3,
      "v_number": 3,
      "tense": 1,
      "tense_str": "FUTURE",
      "gender": -1,
      "number": -1,
      "case": -1
    },
    {
      "id": 19,
      "word": "around",
      "lemma": "around",
      "pos": "ADV",
      "dep": "advmod",
      "node_type": 2,
      "node_type_str": "DESCRIPTOR",
      "okm_notation": "[d:around]",
      "ambiguous": false,
      "gender": -1,
      "number": -1,
      "case": -1,
      "person": -1,
      "tense": 0
    },
    {
      "id": 20,
      "word": "600",
      "lemma": "600",
      "pos": "NUM",
      "dep": "nummod",
      "node_type": 2,
      "node_type_str": "DESCRIPTOR",
      "okm_notation": "[d:600]",
      "ambiguous": false,
      "gender": -1,
      "number": -1,
      "case": -1,
      "person": -1,
      "tense": 0
    },
    {
      "id": 21,
      "word": "beds",
      "lemma": "bed",
      "pos": "NOUN",
      "dep": "dobj",
      "node_type": 0,
      "node_type_str": "NOUN",
      "okm_notation": "beds(3,3,2)",
      "ambiguous": false,
      "gender": 3,
      "number": 3,
      "case": 2,
      "case_str": "OBJECTIVE",
      "person": -1,
      "tense": 0
    }
  ],
  "edges": [
    {
      "source": 3,
      "target": 1,
      "dep": "det",
      "relation": "DET",
      "case": -1,
      "case_str": "NONE",
      "child_type": "DESCRIPTOR",
      "head_type": "NOUN"
    },
    {
      "source": 3,
      "target": 2,
      "dep": "amod",
      "relation": "AMOD",
      "case": -1,
      "case_str": "NONE",
      "child_type": "DESCRIPTOR",
      "head_type": "NOUN"
    },
    {
      "source": 4,
      "target": 0,
      "dep": "advmod",
      "relation": "ADVMOD",
      "case": -1,
      "case_str": "NONE",
      "child_type": "DESCRIPTOR",
      "head_type": "VERB"
    },
    {
      "source": 4,
      "target": 3,
      "dep": "nsubj",
      "relation": "SUBJECT_OF",
      "case": 1,
      "case_str": "SUBJECTIVE",
      "child_type": "NOUN",
      "head_type": "VERB"
    },
    {
      "source": 4,
      "target": 5,
      "dep": "acomp",
      "relation": "ACOMP",
      "case": -1,
      "case_str": "NONE",
      "child_type": "DESCRIPTOR",
      "head_type": "VERB"
    },
    {
      "source": 7,
      "target": 8,
      "dep": "prep",
      "relation": "PREP",
      "case": -1,
      "case_str": "NONE",
      "child_type": "DESCRIPTOR",
      "head_type": "DESCRIPTOR"
    },
    {
      "source": 8,
      "target": 10,
      "dep": "pobj",
      "relation": "INSTRUMENT_OF",
      "case": 3,
      "case_str": "INSTRUMENTAL",
      "child_type": "NOUN",
      "head_type": "DESCRIPTOR"
    },
    {
      "source": 10,
      "target": 9,
      "dep": "det",
      "relation": "DET",
      "case": -1,
      "case_str": "NONE",
      "child_type": "DESCRIPTOR",
      "head_type": "NOUN"
    },
    {
      "source": 10,
      "target": 11,
      "dep": "prep",
      "relation": "PREP",
      "case": -1,
      "case_str": "NONE",
      "child_type": "DESCRIPTOR",
      "head_type": "NOUN"
    },
    {
      "source": 11,
      "target": 13,
      "dep": "pobj",
      "relation": "LOCATED_AT",
      "case": 7,
      "case_str": "LOCATIVE",
      "child_type": "NOUN",
      "head_type": "DESCRIPTOR"
    },
    {
      "source": 13,
      "target": 12,
      "dep": "compound",
      "relation": "POSSESSES",
      "case": 6,
      "case_str": "GENITIVE",
      "child_type": "NOUN",
      "head_type": "NOUN"
    },
    {
      "source": 16,
      "target": 15,
      "dep": "det",
      "relation": "DET",
      "case": -1,
      "case_str": "NONE",
      "child_type": "DESCRIPTOR",
      "head_type": "NOUN"
    },
    {
      "source": 18,
      "target": 4,
      "dep": "advcl",
      "relation": "ADVCL",
      "case": -1,
      "case_str": "NONE",
      "child_type": "VERB",
      "head_type": "VERB"
    },
    {
      "source": 18,
      "target": 7,
      "dep": "prep",
      "relation": "PREP",
      "case": -1,
      "case_str": "NONE",
      "child_type": "DESCRIPTOR",
      "head_type": "VERB"
    },
    {
      "source": 18,
      "target": 16,
      "dep": "nsubj",
      "relation": "SUBJECT_OF",
      "case": 1,
      "case_str": "SUBJECTIVE",
      "child_type": "NOUN",
      "head_type": "VERB"
    },
    {
      "source": 18,
      "target": 17,
      "dep": "aux",
      "relation": "AUX",
      "case": -1,
      "case_str": "NONE",
      "child_type": "VERB",
      "head_type": "VERB"
    },
    {
      "source": 18,
      "target": 21,
      "dep": "dobj",
      "relation": "OBJECT_OF",
      "case": 2,
      "case_str": "OBJECTIVE",
      "child_type": "NOUN",
      "head_type": "VERB"
    },
    {
      "source": 20,
      "target": 19,
      "dep": "advmod",
      "relation": "ADVMOD",
      "case": -1,
      "case_str": "NONE",
      "child_type": "DESCRIPTOR",
      "head_type": "DESCRIPTOR"
    },
    {
      "source": 21,
      "target": 20,
      "dep": "nummod",
      "relation": "NUMMOD",
      "case": -1,
      "case_str": "NONE",
      "child_type": "DESCRIPTOR",
      "head_type": "NOUN"
    }
  ],
  "meta": {
    "okm_version": "1.0",
    "sentence": "When the new hospital is complete , along with the renovations at John Sealy , both complexes will have around 600 beds ."
  }
}